updater4pyi/__init__.py
updater4pyi/cacert.pem
updater4pyi/upd_core.py
updater4pyi/upd_defs.py
updater4pyi/upd_downloader.py
updater4pyi/upd_iface.py
updater4pyi/upd_iface_pyqt4.py
updater4pyi/upd_log.py
updater4pyi/upd_sign.py
updater4pyi/upd_source.py
updater4pyi/upd_version.py
updater4pyi/util.py
updater4pyi/installers/unix/do_install.sh
updater4pyi/installers/win/do_install.exe.zip
updater4pyi-0.7.dist-info/DESCRIPTION.rst
updater4pyi-0.7.dist-info/METADATA
updater4pyi-0.7.dist-info/metadata.json
updater4pyi-0.7.dist-info/RECORD
updater4pyi-0.7.dist-info/top_level.txt
updater4pyi-0.7.dist-info/WHEEL
