Metadata-Version: 2.0
Name: updater4pyi
Version: 0.7
Summary: Lightweight library for software auto-update for applications frozen with pyinstaller
Home-page: https://github.com/phfaist/updater4pyi/
Author: Philippe Faist
Author-email: philippe.faist@bluewin.ch
License: BSD
Platform: UNKNOWN
Classifier: Development Status :: 4 - Beta
Classifier: License :: OSI Approved :: BSD License
Classifier: Programming Language :: Python
Classifier: Operating System :: MacOS :: MacOS X
Classifier: Operating System :: Microsoft :: Windows
Classifier: Operating System :: POSIX :: Linux
Classifier: Intended Audience :: Developers
Classifier: Topic :: Software Development
Classifier: Topic :: Software Development :: Libraries :: Python Modules
Classifier: Topic :: System :: Software Distribution
